cdk_create_ami/__init__.py
cdk_create_ami/py.typed
cdk_create_ami/_jsii/__init__.py
cdk_create_ami/_jsii/cdk-create-ami@0.0.192.jsii.tgz
cdk_create_ami-0.0.192.dist-info/LICENSE
cdk_create_ami-0.0.192.dist-info/METADATA
cdk_create_ami-0.0.192.dist-info/WHEEL
cdk_create_ami-0.0.192.dist-info/top_level.txt
cdk_create_ami-0.0.192.dist-info/RECORD
